tool.py
zxtestlib/__init__.py
zxtestlib/zxtest.py
zxtestlib-1.0.0.dist-info/METADATA
zxtestlib-1.0.0.dist-info/RECORD
zxtestlib-1.0.0.dist-info/WHEEL
zxtestlib-1.0.0.dist-info/top_level.txt
