Metadata-Version: 2.1
Name: zxtestlib
Version: 1.0.0
Summary: This is a test lib
Home-page: https://gibhut.com/zhongxi/python_code
Author: zx
Author-email: 870121209@qq.com
License: UNKNOWN
Platform: UNKNOWN
